django_cassandra/common/__init__.py
django_cassandra/common/exception_handler.py
django_cassandra/common/filters.py
django_cassandra/common/messages.py
django_cassandra/common/models.py
django_cassandra/common/paginators.py
django_cassandra/common/remote.py
django_cassandra/common/responses.py
django_cassandra/common/serializers.py
django_cassandra/common/utilities.py
django_cassandra/common/views.py
django_cassandra_common-0.0.2.dist-info/LICENSE
django_cassandra_common-0.0.2.dist-info/METADATA
django_cassandra_common-0.0.2.dist-info/WHEEL
django_cassandra_common-0.0.2.dist-info/top_level.txt
django_cassandra_common-0.0.2.dist-info/RECORD
