Metadata-Version: 2.1
Name: django-cassandra-common
Version: 0.0.2
Summary: Common classes I have found useful to develop with Django and Cassandra
Home-page: https://github.com/didier47/django-cassandra-common
Author: Didier Gaona
Author-email: didiergaona@gmail.com
License: GNU General Public License v3.0
Download-URL: https://github.com/didier47/django-cassandra-common/archive/0.0.1.tar.gz
Platform: UNKNOWN
Classifier: Development Status :: 3 - Alpha
Classifier: Intended Audience :: Developers
Classifier: Topic :: Software Development :: Build Tools
Classifier: License :: OSI Approved :: GNU General Public License v3 or later (GPLv3+)
Classifier: Programming Language :: Python :: 3
Classifier: Programming Language :: Python :: 3.4
Classifier: Programming Language :: Python :: 3.5
Classifier: Programming Language :: Python :: 3.6
Classifier: Programming Language :: Python :: 3.7
Classifier: Programming Language :: Python :: 3.8
Requires-Dist: Django (>=3.0.6)
Requires-Dist: djangorestframework (>=3.11.0)
Requires-Dist: cassandra-driver (>=3.23.0)
Requires-Dist: requests (>=2.23.0)
Requires-Dist: django-filter (>=2.3.0)
Requires-Dist: setuptools (>=46.4.0)
Requires-Dist: django-cassandra-engine (>=1.6.1)
Requires-Dist: drf-yasg (>=1.17.1)
